kaladeno/__init__.py
kaladeno/courses.py
kaladeno/utils.py
kaladeno-0.1.0.dist-info/METADATA
kaladeno-0.1.0.dist-info/WHEEL
kaladeno-0.1.0.dist-info/top_level.txt
kaladeno-0.1.0.dist-info/RECORD
