Metadata-Version: 2.1
Name: kaladeno
Version: 0.1.0
Summary: Una biblioteca para consultar cursos
Home-page: https://hack4u.io
Author: Sergio Llorente
